adafruit_circuitpython_pastebin-1.0.11.dist-info/licenses/LICENSE
adafruit_pastebin/__init__.py
adafruit_pastebin/adafruit_io.py
adafruit_pastebin/gist.py
adafruit_pastebin/pastebin.py
adafruit_circuitpython_pastebin-1.0.11.dist-info/METADATA
adafruit_circuitpython_pastebin-1.0.11.dist-info/WHEEL
adafruit_circuitpython_pastebin-1.0.11.dist-info/top_level.txt
adafruit_circuitpython_pastebin-1.0.11.dist-info/RECORD
